airbyte_python_helper.py
airbyte_api_wrapper-0.0.3.dist-info/LICENSE
airbyte_api_wrapper-0.0.3.dist-info/METADATA
airbyte_api_wrapper-0.0.3.dist-info/WHEEL
airbyte_api_wrapper-0.0.3.dist-info/top_level.txt
airbyte_api_wrapper-0.0.3.dist-info/RECORD
