Metadata-Version: 2.1
Name: airbyte-api-wrapper
Version: 0.0.3
Summary: A wrapper for Airbyte API.
Author-email: Thibaut de Broca <thibaut@grooptown.com>
Project-URL: Homepage, https://github.com/tdebroc/airbyte-api-wrapper
Project-URL: Bug Tracker, https://github.com/tdebroc/airbyte-api-wrapper/issues
Classifier: Programming Language :: Python :: 3
Classifier: License :: OSI Approved :: MIT License
Classifier: Operating System :: OS Independent
Requires-Python: >=3.7
License-File: LICENSE
